MANIFEST.in
README.md
setup.py
pyboxapi/__init__.py
pyboxapi.egg-info/PKG-INFO
pyboxapi.egg-info/SOURCES.txt
pyboxapi.egg-info/dependency_links.txt
pyboxapi.egg-info/not-zip-safe
pyboxapi.egg-info/top_level.txt