Metadata-Version: 1.0
Name: pyboxapi
Version: 0.1.4
Summary: Python Box.com API
Home-page: http://github.com/tachang/pyboxapi/
Author: Jeff Tchang
Author-email: jeff.tchang@gmail.com
License: UNKNOWN
Platform: UNKNOWN
Classifier: Development Status :: 4 - Beta
Classifier: Intended Audience :: Developers
Classifier: License :: OSI Approved :: BSD License
Classifier: Operating System :: OS Independent
Classifier: Programming Language :: Python
Classifier: Topic :: Utilities
